{"errors":[],"warnings":[],"namedChunkGroups":{"app":{"chunks":[7,0,2],"assets":["webpack-runtime-b1334645ae0d0b0c73c2.js","webpack-runtime-b1334645ae0d0b0c73c2.js.map","commons-3259632a947742207289.js","commons-3259632a947742207289.js.map","app-139abd4c6cd37c653798.js","app-139abd4c6cd37c653798.js.map"],"children":{},"childAssets":{}},"component---src-templates-blog-post-js":{"chunks":[1,0,6],"assets":["styles.2a90ad25a146c7691e70.css","styles-04367093563754e2a6bc.js","styles-04367093563754e2a6bc.js.map","commons-3259632a947742207289.js","commons-3259632a947742207289.js.map","component---src-templates-blog-post-js-c58f32579d78d902f990.js","component---src-templates-blog-post-js-c58f32579d78d902f990.js.map"],"children":{},"childAssets":{}},"component---src-pages-404-js":{"chunks":[1,0,3],"assets":["styles.2a90ad25a146c7691e70.css","styles-04367093563754e2a6bc.js","styles-04367093563754e2a6bc.js.map","commons-3259632a947742207289.js","commons-3259632a947742207289.js.map","component---src-pages-404-js-de147e2a411283ceee16.js","component---src-pages-404-js-de147e2a411283ceee16.js.map"],"children":{},"childAssets":{}},"component---src-pages-index-js":{"chunks":[1,0,4],"assets":["styles.2a90ad25a146c7691e70.css","styles-04367093563754e2a6bc.js","styles-04367093563754e2a6bc.js.map","commons-3259632a947742207289.js","commons-3259632a947742207289.js.map","component---src-pages-index-js-7401e9a0d294cdd1014f.js","component---src-pages-index-js-7401e9a0d294cdd1014f.js.map"],"children":{},"childAssets":{}},"component---src-pages-posts-js":{"chunks":[1,0,5],"assets":["styles.2a90ad25a146c7691e70.css","styles-04367093563754e2a6bc.js","styles-04367093563754e2a6bc.js.map","commons-3259632a947742207289.js","commons-3259632a947742207289.js.map","component---src-pages-posts-js-16b466bb57dfe91eb50e.js","component---src-pages-posts-js-16b466bb57dfe91eb50e.js.map"],"children":{},"childAssets":{}}},"assetsByChunkName":{"app":["webpack-runtime-b1334645ae0d0b0c73c2.js","commons-3259632a947742207289.js","app-139abd4c6cd37c653798.js"],"component---src-templates-blog-post-js":["styles.2a90ad25a146c7691e70.css","styles-04367093563754e2a6bc.js","commons-3259632a947742207289.js","component---src-templates-blog-post-js-c58f32579d78d902f990.js"],"component---src-pages-404-js":["styles.2a90ad25a146c7691e70.css","styles-04367093563754e2a6bc.js","commons-3259632a947742207289.js","component---src-pages-404-js-de147e2a411283ceee16.js"],"component---src-pages-index-js":["styles.2a90ad25a146c7691e70.css","styles-04367093563754e2a6bc.js","commons-3259632a947742207289.js","component---src-pages-index-js-7401e9a0d294cdd1014f.js"],"component---src-pages-posts-js":["styles.2a90ad25a146c7691e70.css","styles-04367093563754e2a6bc.js","commons-3259632a947742207289.js","component---src-pages-posts-js-16b466bb57dfe91eb50e.js"]}}